<?xml version="1.0" encoding="UTF-8" standalone="yes"?>
<template encoding-version="1.3">
    <description>A dataflow to merge all the files from ADLSgen2 storage into one file and ingest back to Azure Data Lake Storagegen2.</description>
    <groupId>1d993fab-f202-15b0-f496-be94d00f1489</groupId>
    <name>mergeAdlsGen2files</name>
    <snippet>
        <connections>
            <id>49d2d34c-44f1-3abc-0000-000000000000</id>
            <parentGroupId>e6175b51-fded-3089-0000-000000000000</parentGroupId>
            <backPressureDataSizeThreshold>1 GB</backPressureDataSizeThreshold>
            <backPressureObjectThreshold>10000</backPressureObjectThreshold>
            <destination>
                <groupId>47949e15-38fb-398a-0000-000000000000</groupId>
                <id>d1c08996-0249-3142-0000-000000000000</id>
                <type>INPUT_PORT</type>
            </destination>
            <flowFileExpiration>0 sec</flowFileExpiration>
            <labelIndex>1</labelIndex>
            <loadBalanceCompression>DO_NOT_COMPRESS</loadBalanceCompression>
            <loadBalancePartitionAttribute></loadBalancePartitionAttribute>
            <loadBalanceStatus>LOAD_BALANCE_NOT_CONFIGURED</loadBalanceStatus>
            <loadBalanceStrategy>DO_NOT_LOAD_BALANCE</loadBalanceStrategy>
            <name></name>
            <source>
                <groupId>c58e1e77-0375-3066-0000-000000000000</groupId>
                <id>9eacc986-9f6e-3c13-0000-000000000000</id>
                <type>OUTPUT_PORT</type>
            </source>
            <zIndex>0</zIndex>
        </connections>
        <connections>
            <id>f74cb871-f58b-34ad-0000-000000000000</id>
            <parentGroupId>e6175b51-fded-3089-0000-000000000000</parentGroupId>
            <backPressureDataSizeThreshold>1 GB</backPressureDataSizeThreshold>
            <backPressureObjectThreshold>10000</backPressureObjectThreshold>
            <destination>
                <groupId>c58e1e77-0375-3066-0000-000000000000</groupId>
                <id>406d35c8-7f6f-336c-0000-000000000000</id>
                <type>INPUT_PORT</type>
            </destination>
            <flowFileExpiration>0 sec</flowFileExpiration>
            <labelIndex>1</labelIndex>
            <loadBalanceCompression>DO_NOT_COMPRESS</loadBalanceCompression>
            <loadBalancePartitionAttribute></loadBalancePartitionAttribute>
            <loadBalanceStatus>LOAD_BALANCE_NOT_CONFIGURED</loadBalanceStatus>
            <loadBalanceStrategy>DO_NOT_LOAD_BALANCE</loadBalanceStrategy>
            <name></name>
            <source>
                <groupId>05f5c60b-2169-3db4-0000-000000000000</groupId>
                <id>e264b459-bf97-37b1-0000-000000000000</id>
                <type>OUTPUT_PORT</type>
            </source>
            <zIndex>0</zIndex>
        </connections>
        <controllerServices>
            <id>5cf3cc3e-1b45-306e-0000-000000000000</id>
            <parentGroupId>e6175b51-fded-3089-0000-000000000000</parentGroupId>
            <bundle>
                <artifact>nifi-azure-nar</artifact>
                <group>org.apache.nifi</group>
                <version>1.12.1</version>
            </bundle>
            <comments></comments>
            <descriptors>
                <entry>
                    <key>storage-account-name</key>
                    <value>
                        <name>storage-account-name</name>
                    </value>
                </entry>
                <entry>
                    <key>storage-endpoint-suffix</key>
                    <value>
                        <name>storage-endpoint-suffix</name>
                    </value>
                </entry>
                <entry>
                    <key>storage-account-key</key>
                    <value>
                        <name>storage-account-key</name>
                    </value>
                </entry>
                <entry>
                    <key>storage-sas-token</key>
                    <value>
                        <name>storage-sas-token</name>
                    </value>
                </entry>
                <entry>
                    <key>storage-use-managed-identity</key>
                    <value>
                        <name>storage-use-managed-identity</name>
                    </value>
                </entry>
            </descriptors>
            <name>ADLSCredentialsControllerService</name>
            <persistsState>false</persistsState>
            <properties>
                <entry>
                    <key>storage-account-name</key>
                </entry>
                <entry>
                    <key>storage-endpoint-suffix</key>
                    <value>dfs.core.windows.net</value>
                </entry>
                <entry>
                    <key>storage-account-key</key>
                </entry>
                <entry>
                    <key>storage-sas-token</key>
                </entry>
                <entry>
                    <key>storage-use-managed-identity</key>
                    <value>false</value>
                </entry>
            </properties>
            <state>ENABLED</state>
            <type>org.apache.nifi.services.azure.storage.ADLSCredentialsControllerService</type>
        </controllerServices>
        <processGroups>
            <id>05f5c60b-2169-3db4-0000-000000000000</id>
            <parentGroupId>e6175b51-fded-3089-0000-000000000000</parentGroupId>
            <position>
                <x>0.0</x>
                <y>0.0</y>
            </position>
            <comments></comments>
            <contents>
                <connections>
                    <id>bb404735-e845-32b7-0000-000000000000</id>
                    <parentGroupId>05f5c60b-2169-3db4-0000-000000000000</parentGroupId>
                    <backPressureDataSizeThreshold>1 GB</backPressureDataSizeThreshold>
                    <backPressureObjectThreshold>10000</backPressureObjectThreshold>
                    <destination>
                        <groupId>05f5c60b-2169-3db4-0000-000000000000</groupId>
                        <id>e264b459-bf97-37b1-0000-000000000000</id>
                        <type>OUTPUT_PORT</type>
                    </destination>
                    <flowFileExpiration>0 sec</flowFileExpiration>
                    <labelIndex>1</labelIndex>
                    <loadBalanceCompression>DO_NOT_COMPRESS</loadBalanceCompression>
                    <loadBalancePartitionAttribute></loadBalancePartitionAttribute>
                    <loadBalanceStatus>LOAD_BALANCE_NOT_CONFIGURED</loadBalanceStatus>
                    <loadBalanceStrategy>DO_NOT_LOAD_BALANCE</loadBalanceStrategy>
                    <name></name>
                    <selectedRelationships>success</selectedRelationships>
                    <source>
                        <groupId>05f5c60b-2169-3db4-0000-000000000000</groupId>
                        <id>e78e2814-f574-335a-0000-000000000000</id>
                        <type>PROCESSOR</type>
                    </source>
                    <zIndex>0</zIndex>
                </connections>
                <connections>
                    <id>ee38badd-546e-379f-0000-000000000000</id>
                    <parentGroupId>05f5c60b-2169-3db4-0000-000000000000</parentGroupId>
                    <backPressureDataSizeThreshold>1 GB</backPressureDataSizeThreshold>
                    <backPressureObjectThreshold>10000</backPressureObjectThreshold>
                    <destination>
                        <groupId>05f5c60b-2169-3db4-0000-000000000000</groupId>
                        <id>e78e2814-f574-335a-0000-000000000000</id>
                        <type>PROCESSOR</type>
                    </destination>
                    <flowFileExpiration>0 sec</flowFileExpiration>
                    <labelIndex>1</labelIndex>
                    <loadBalanceCompression>DO_NOT_COMPRESS</loadBalanceCompression>
                    <loadBalancePartitionAttribute></loadBalancePartitionAttribute>
                    <loadBalanceStatus>LOAD_BALANCE_NOT_CONFIGURED</loadBalanceStatus>
                    <loadBalanceStrategy>DO_NOT_LOAD_BALANCE</loadBalanceStrategy>
                    <name></name>
                    <selectedRelationships>success</selectedRelationships>
                    <source>
                        <groupId>05f5c60b-2169-3db4-0000-000000000000</groupId>
                        <id>4c1686eb-bf23-3af4-0000-000000000000</id>
                        <type>PROCESSOR</type>
                    </source>
                    <zIndex>0</zIndex>
                </connections>
                <labels>
                    <id>4a48e032-8883-3154-0000-000000000000</id>
                    <parentGroupId>05f5c60b-2169-3db4-0000-000000000000</parentGroupId>
                    <position>
                        <x>160.0</x>
                        <y>-200.0</y>
                    </position>
                    <height>64.0</height>
                    <label>Fetches all the files from adls dir</label>
                    <style>
                        <entry>
                            <key>font-size</key>
                            <value>16px</value>
                        </entry>
                    </style>
                    <width>280.0</width>
                </labels>
                <labels>
                    <id>cd64a829-e714-30c8-0000-000000000000</id>
                    <parentGroupId>05f5c60b-2169-3db4-0000-000000000000</parentGroupId>
                    <position>
                        <x>400.0</x>
                        <y>104.0</y>
                    </position>
                    <height>48.0</height>
                    <label>Lists all the files from adls</label>
                    <style>
                        <entry>
                            <key>font-size</key>
                            <value>16px</value>
                        </entry>
                    </style>
                    <width>208.0</width>
                </labels>
                <outputPorts>
                    <id>e264b459-bf97-37b1-0000-000000000000</id>
                    <parentGroupId>05f5c60b-2169-3db4-0000-000000000000</parentGroupId>
                    <position>
                        <x>848.0</x>
                        <y>-128.0</y>
                    </position>
                    <concurrentlySchedulableTaskCount>1</concurrentlySchedulableTaskCount>
                    <name>ADLSFetchedFiles</name>
                    <state>STOPPED</state>
                    <type>OUTPUT_PORT</type>
                </outputPorts>
                <processors>
                    <id>4c1686eb-bf23-3af4-0000-000000000000</id>
                    <parentGroupId>05f5c60b-2169-3db4-0000-000000000000</parentGroupId>
                    <position>
                        <x>200.0</x>
                        <y>136.0</y>
                    </position>
                    <bundle>
                        <artifact>nifi-azure-nar</artifact>
                        <group>org.apache.nifi</group>
                        <version>1.12.1</version>
                    </bundle>
                    <config>
                        <bulletinLevel>WARN</bulletinLevel>
                        <comments></comments>
                        <concurrentlySchedulableTaskCount>1</concurrentlySchedulableTaskCount>
                        <descriptors>
                            <entry>
<key>adls-credentials-service</key>
<value>
    <identifiesControllerService>org.apache.nifi.services.azure.storage.ADLSCredentialsService</identifiesControllerService>
    <name>adls-credentials-service</name>
</value>
                            </entry>
                            <entry>
<key>filesystem-name</key>
<value>
    <name>filesystem-name</name>
</value>
                            </entry>
                            <entry>
<key>directory-name</key>
<value>
    <name>directory-name</name>
</value>
                            </entry>
                            <entry>
<key>recurse-subdirectories</key>
<value>
    <name>recurse-subdirectories</name>
</value>
                            </entry>
                            <entry>
<key>file-filter</key>
<value>
    <name>file-filter</name>
</value>
                            </entry>
                            <entry>
<key>path-filter</key>
<value>
    <name>path-filter</name>
</value>
                            </entry>
                            <entry>
<key>record-writer</key>
<value>
    <identifiesControllerService>org.apache.nifi.serialization.RecordSetWriterFactory</identifiesControllerService>
    <name>record-writer</name>
</value>
                            </entry>
                            <entry>
<key>listing-strategy</key>
<value>
    <name>listing-strategy</name>
</value>
                            </entry>
                            <entry>
<key>et-state-cache</key>
<value>
    <identifiesControllerService>org.apache.nifi.distributed.cache.client.DistributedMapCacheClient</identifiesControllerService>
    <name>et-state-cache</name>
</value>
                            </entry>
                            <entry>
<key>et-time-window</key>
<value>
    <name>et-time-window</name>
</value>
                            </entry>
                            <entry>
<key>et-initial-listing-target</key>
<value>
    <name>et-initial-listing-target</name>
</value>
                            </entry>
                        </descriptors>
                        <executionNode>PRIMARY</executionNode>
                        <lossTolerant>false</lossTolerant>
                        <penaltyDuration>30 sec</penaltyDuration>
                        <properties>
                            <entry>
<key>adls-credentials-service</key>
<value>5cf3cc3e-1b45-306e-0000-000000000000</value>
                            </entry>
                            <entry>
<key>filesystem-name</key>
<value>files</value>
                            </entry>
                            <entry>
<key>directory-name</key>
<value>csvs</value>
                            </entry>
                            <entry>
<key>recurse-subdirectories</key>
<value>true</value>
                            </entry>
                            <entry>
<key>file-filter</key>
                            </entry>
                            <entry>
<key>path-filter</key>
                            </entry>
                            <entry>
<key>record-writer</key>
                            </entry>
                            <entry>
<key>listing-strategy</key>
<value>timestamps</value>
                            </entry>
                            <entry>
<key>et-state-cache</key>
                            </entry>
                            <entry>
<key>et-time-window</key>
<value>3 hours</value>
                            </entry>
                            <entry>
<key>et-initial-listing-target</key>
<value>all</value>
                            </entry>
                        </properties>
                        <runDurationMillis>0</runDurationMillis>
                        <schedulingPeriod>0 sec</schedulingPeriod>
                        <schedulingStrategy>TIMER_DRIVEN</schedulingStrategy>
                        <yieldDuration>1 sec</yieldDuration>
                    </config>
                    <executionNodeRestricted>true</executionNodeRestricted>
                    <name>ListAzureDataLakeStorage</name>
                    <relationships>
                        <autoTerminate>false</autoTerminate>
                        <name>success</name>
                    </relationships>
                    <state>STOPPED</state>
                    <style/>
                    <type>org.apache.nifi.processors.azure.storage.ListAzureDataLakeStorage</type>
                </processors>
                <processors>
                    <id>e78e2814-f574-335a-0000-000000000000</id>
                    <parentGroupId>05f5c60b-2169-3db4-0000-000000000000</parentGroupId>
                    <position>
                        <x>200.0</x>
                        <y>-168.0</y>
                    </position>
                    <bundle>
                        <artifact>nifi-azure-nar</artifact>
                        <group>org.apache.nifi</group>
                        <version>1.12.1</version>
                    </bundle>
                    <config>
                        <bulletinLevel>WARN</bulletinLevel>
                        <comments></comments>
                        <concurrentlySchedulableTaskCount>1</concurrentlySchedulableTaskCount>
                        <descriptors>
                            <entry>
<key>adls-credentials-service</key>
<value>
    <identifiesControllerService>org.apache.nifi.services.azure.storage.ADLSCredentialsService</identifiesControllerService>
    <name>adls-credentials-service</name>
</value>
                            </entry>
                            <entry>
<key>filesystem-name</key>
<value>
    <name>filesystem-name</name>
</value>
                            </entry>
                            <entry>
<key>directory-name</key>
<value>
    <name>directory-name</name>
</value>
                            </entry>
                            <entry>
<key>file-name</key>
<value>
    <name>file-name</name>
</value>
                            </entry>
                        </descriptors>
                        <executionNode>ALL</executionNode>
                        <lossTolerant>false</lossTolerant>
                        <penaltyDuration>30 sec</penaltyDuration>
                        <properties>
                            <entry>
<key>adls-credentials-service</key>
<value>5cf3cc3e-1b45-306e-0000-000000000000</value>
                            </entry>
                            <entry>
<key>filesystem-name</key>
<value>files</value>
                            </entry>
                            <entry>
<key>directory-name</key>
<value>csvs</value>
                            </entry>
                            <entry>
<key>file-name</key>
<value>${azure.filename}</value>
                            </entry>
                        </properties>
                        <runDurationMillis>0</runDurationMillis>
                        <schedulingPeriod>0 sec</schedulingPeriod>
                        <schedulingStrategy>TIMER_DRIVEN</schedulingStrategy>
                        <yieldDuration>1 sec</yieldDuration>
                    </config>
                    <executionNodeRestricted>false</executionNodeRestricted>
                    <name>FetchAzureDataLakeStorage</name>
                    <relationships>
                        <autoTerminate>true</autoTerminate>
                        <name>failure</name>
                    </relationships>
                    <relationships>
                        <autoTerminate>false</autoTerminate>
                        <name>success</name>
                    </relationships>
                    <state>STOPPED</state>
                    <style/>
                    <type>org.apache.nifi.processors.azure.storage.FetchAzureDataLakeStorage</type>
                </processors>
            </contents>
            <flowfileConcurrency>UNBOUNDED</flowfileConcurrency>
            <flowfileOutboundPolicy>STREAM_WHEN_AVAILABLE</flowfileOutboundPolicy>
            <name>FetchFromADLS</name>
            <variables/>
        </processGroups>
        <processGroups>
            <id>47949e15-38fb-398a-0000-000000000000</id>
            <parentGroupId>e6175b51-fded-3089-0000-000000000000</parentGroupId>
            <position>
                <x>680.0</x>
                <y>312.0</y>
            </position>
            <comments></comments>
            <contents>
                <connections>
                    <id>4b659f6c-932a-3ce3-0000-000000000000</id>
                    <parentGroupId>47949e15-38fb-398a-0000-000000000000</parentGroupId>
                    <backPressureDataSizeThreshold>1 GB</backPressureDataSizeThreshold>
                    <backPressureObjectThreshold>10000</backPressureObjectThreshold>
                    <destination>
                        <groupId>47949e15-38fb-398a-0000-000000000000</groupId>
                        <id>e543bfbe-8b02-3b53-0000-000000000000</id>
                        <type>PROCESSOR</type>
                    </destination>
                    <flowFileExpiration>0 sec</flowFileExpiration>
                    <labelIndex>1</labelIndex>
                    <loadBalanceCompression>DO_NOT_COMPRESS</loadBalanceCompression>
                    <loadBalancePartitionAttribute></loadBalancePartitionAttribute>
                    <loadBalanceStatus>LOAD_BALANCE_NOT_CONFIGURED</loadBalanceStatus>
                    <loadBalanceStrategy>DO_NOT_LOAD_BALANCE</loadBalanceStrategy>
                    <name></name>
                    <source>
                        <groupId>47949e15-38fb-398a-0000-000000000000</groupId>
                        <id>d1c08996-0249-3142-0000-000000000000</id>
                        <type>INPUT_PORT</type>
                    </source>
                    <zIndex>0</zIndex>
                </connections>
                <connections>
                    <id>c10967f4-c354-3383-0000-000000000000</id>
                    <parentGroupId>47949e15-38fb-398a-0000-000000000000</parentGroupId>
                    <backPressureDataSizeThreshold>1 GB</backPressureDataSizeThreshold>
                    <backPressureObjectThreshold>10000</backPressureObjectThreshold>
                    <destination>
                        <groupId>47949e15-38fb-398a-0000-000000000000</groupId>
                        <id>103027a4-de44-387b-0000-000000000000</id>
                        <type>FUNNEL</type>
                    </destination>
                    <flowFileExpiration>0 sec</flowFileExpiration>
                    <labelIndex>1</labelIndex>
                    <loadBalanceCompression>DO_NOT_COMPRESS</loadBalanceCompression>
                    <loadBalancePartitionAttribute></loadBalancePartitionAttribute>
                    <loadBalanceStatus>LOAD_BALANCE_NOT_CONFIGURED</loadBalanceStatus>
                    <loadBalanceStrategy>DO_NOT_LOAD_BALANCE</loadBalanceStrategy>
                    <name></name>
                    <selectedRelationships>success</selectedRelationships>
                    <source>
                        <groupId>47949e15-38fb-398a-0000-000000000000</groupId>
                        <id>e543bfbe-8b02-3b53-0000-000000000000</id>
                        <type>PROCESSOR</type>
                    </source>
                    <zIndex>0</zIndex>
                </connections>
                <connections>
                    <id>dc9579ff-9fdd-330a-0000-000000000000</id>
                    <parentGroupId>47949e15-38fb-398a-0000-000000000000</parentGroupId>
                    <backPressureDataSizeThreshold>1 GB</backPressureDataSizeThreshold>
                    <backPressureObjectThreshold>10000</backPressureObjectThreshold>
                    <destination>
                        <groupId>47949e15-38fb-398a-0000-000000000000</groupId>
                        <id>4fa8a611-f30a-307b-0000-000000000000</id>
                        <type>FUNNEL</type>
                    </destination>
                    <flowFileExpiration>0 sec</flowFileExpiration>
                    <labelIndex>1</labelIndex>
                    <loadBalanceCompression>DO_NOT_COMPRESS</loadBalanceCompression>
                    <loadBalancePartitionAttribute></loadBalancePartitionAttribute>
                    <loadBalanceStatus>LOAD_BALANCE_NOT_CONFIGURED</loadBalanceStatus>
                    <loadBalanceStrategy>DO_NOT_LOAD_BALANCE</loadBalanceStrategy>
                    <name></name>
                    <selectedRelationships>failure</selectedRelationships>
                    <source>
                        <groupId>47949e15-38fb-398a-0000-000000000000</groupId>
                        <id>e543bfbe-8b02-3b53-0000-000000000000</id>
                        <type>PROCESSOR</type>
                    </source>
                    <zIndex>0</zIndex>
                </connections>
                <funnels>
                    <id>103027a4-de44-387b-0000-000000000000</id>
                    <parentGroupId>47949e15-38fb-398a-0000-000000000000</parentGroupId>
                    <position>
                        <x>1736.0</x>
                        <y>448.0</y>
                    </position>
                </funnels>
                <funnels>
                    <id>4fa8a611-f30a-307b-0000-000000000000</id>
                    <parentGroupId>47949e15-38fb-398a-0000-000000000000</parentGroupId>
                    <position>
                        <x>1744.0</x>
                        <y>672.0</y>
                    </position>
                </funnels>
                <inputPorts>
                    <id>d1c08996-0249-3142-0000-000000000000</id>
                    <parentGroupId>47949e15-38fb-398a-0000-000000000000</parentGroupId>
                    <position>
                        <x>960.0</x>
                        <y>280.0</y>
                    </position>
                    <comments></comments>
                    <concurrentlySchedulableTaskCount>1</concurrentlySchedulableTaskCount>
                    <name>merged_file</name>
                    <state>STOPPED</state>
                    <type>INPUT_PORT</type>
                </inputPorts>
                <labels>
                    <id>75e968ab-1826-3a03-0000-000000000000</id>
                    <parentGroupId>47949e15-38fb-398a-0000-000000000000</parentGroupId>
                    <position>
                        <x>728.0</x>
                        <y>440.0</y>
                    </position>
                    <height>88.0</height>
                    <label>Configure the ADLS credentials,
file system name 
&amp; folder name</label>
                    <style>
                        <entry>
                            <key>font-size</key>
                            <value>16px</value>
                        </entry>
                    </style>
                    <width>272.0</width>
                </labels>
                <processors>
                    <id>e543bfbe-8b02-3b53-0000-000000000000</id>
                    <parentGroupId>47949e15-38fb-398a-0000-000000000000</parentGroupId>
                    <position>
                        <x>904.0</x>
                        <y>480.0</y>
                    </position>
                    <bundle>
                        <artifact>nifi-azure-nar</artifact>
                        <group>org.apache.nifi</group>
                        <version>1.12.1</version>
                    </bundle>
                    <config>
                        <bulletinLevel>WARN</bulletinLevel>
                        <comments></comments>
                        <concurrentlySchedulableTaskCount>1</concurrentlySchedulableTaskCount>
                        <descriptors>
                            <entry>
<key>adls-credentials-service</key>
<value>
    <identifiesControllerService>org.apache.nifi.services.azure.storage.ADLSCredentialsService</identifiesControllerService>
    <name>adls-credentials-service</name>
</value>
                            </entry>
                            <entry>
<key>filesystem-name</key>
<value>
    <name>filesystem-name</name>
</value>
                            </entry>
                            <entry>
<key>directory-name</key>
<value>
    <name>directory-name</name>
</value>
                            </entry>
                            <entry>
<key>file-name</key>
<value>
    <name>file-name</name>
</value>
                            </entry>
                            <entry>
<key>conflict-resolution-strategy</key>
<value>
    <name>conflict-resolution-strategy</name>
</value>
                            </entry>
                        </descriptors>
                        <executionNode>ALL</executionNode>
                        <lossTolerant>false</lossTolerant>
                        <penaltyDuration>30 sec</penaltyDuration>
                        <properties>
                            <entry>
<key>adls-credentials-service</key>
<value>5cf3cc3e-1b45-306e-0000-000000000000</value>
                            </entry>
                            <entry>
<key>filesystem-name</key>
<value>files</value>
                            </entry>
                            <entry>
<key>directory-name</key>
<value>csvs</value>
                            </entry>
                            <entry>
<key>file-name</key>
<value>${filename}</value>
                            </entry>
                            <entry>
<key>conflict-resolution-strategy</key>
<value>fail</value>
                            </entry>
                        </properties>
                        <runDurationMillis>0</runDurationMillis>
                        <schedulingPeriod>0 sec</schedulingPeriod>
                        <schedulingStrategy>TIMER_DRIVEN</schedulingStrategy>
                        <yieldDuration>1 sec</yieldDuration>
                    </config>
                    <executionNodeRestricted>false</executionNodeRestricted>
                    <name>PutAzureDataLakeStorage</name>
                    <relationships>
                        <autoTerminate>false</autoTerminate>
                        <name>failure</name>
                    </relationships>
                    <relationships>
                        <autoTerminate>false</autoTerminate>
                        <name>success</name>
                    </relationships>
                    <state>STOPPED</state>
                    <style/>
                    <type>org.apache.nifi.processors.azure.storage.PutAzureDataLakeStorage</type>
                </processors>
            </contents>
            <flowfileConcurrency>UNBOUNDED</flowfileConcurrency>
            <flowfileOutboundPolicy>STREAM_WHEN_AVAILABLE</flowfileOutboundPolicy>
            <name>ingest_to_adlsgen2</name>
            <variables/>
        </processGroups>
        <processGroups>
            <id>c58e1e77-0375-3066-0000-000000000000</id>
            <parentGroupId>e6175b51-fded-3089-0000-000000000000</parentGroupId>
            <position>
                <x>0.0</x>
                <y>312.0</y>
            </position>
            <comments></comments>
            <contents>
                <connections>
                    <id>3a728167-b036-3070-0000-000000000000</id>
                    <parentGroupId>c58e1e77-0375-3066-0000-000000000000</parentGroupId>
                    <backPressureDataSizeThreshold>1 GB</backPressureDataSizeThreshold>
                    <backPressureObjectThreshold>10000</backPressureObjectThreshold>
                    <destination>
                        <groupId>c58e1e77-0375-3066-0000-000000000000</groupId>
                        <id>352e925a-21f3-3ca2-0000-000000000000</id>
                        <type>PROCESSOR</type>
                    </destination>
                    <flowFileExpiration>0 sec</flowFileExpiration>
                    <labelIndex>1</labelIndex>
                    <loadBalanceCompression>DO_NOT_COMPRESS</loadBalanceCompression>
                    <loadBalancePartitionAttribute></loadBalancePartitionAttribute>
                    <loadBalanceStatus>LOAD_BALANCE_NOT_CONFIGURED</loadBalanceStatus>
                    <loadBalanceStrategy>DO_NOT_LOAD_BALANCE</loadBalanceStrategy>
                    <name></name>
                    <selectedRelationships>merged</selectedRelationships>
                    <source>
                        <groupId>c58e1e77-0375-3066-0000-000000000000</groupId>
                        <id>08cb882e-6c6c-3ae3-0000-000000000000</id>
                        <type>PROCESSOR</type>
                    </source>
                    <zIndex>0</zIndex>
                </connections>
                <connections>
                    <id>427a13dd-83d5-37bf-0000-000000000000</id>
                    <parentGroupId>c58e1e77-0375-3066-0000-000000000000</parentGroupId>
                    <backPressureDataSizeThreshold>1 GB</backPressureDataSizeThreshold>
                    <backPressureObjectThreshold>10000</backPressureObjectThreshold>
                    <destination>
                        <groupId>c58e1e77-0375-3066-0000-000000000000</groupId>
                        <id>08cb882e-6c6c-3ae3-0000-000000000000</id>
                        <type>PROCESSOR</type>
                    </destination>
                    <flowFileExpiration>0 sec</flowFileExpiration>
                    <labelIndex>1</labelIndex>
                    <loadBalanceCompression>DO_NOT_COMPRESS</loadBalanceCompression>
                    <loadBalancePartitionAttribute></loadBalancePartitionAttribute>
                    <loadBalanceStatus>LOAD_BALANCE_NOT_CONFIGURED</loadBalanceStatus>
                    <loadBalanceStrategy>DO_NOT_LOAD_BALANCE</loadBalanceStrategy>
                    <name></name>
                    <source>
                        <groupId>c58e1e77-0375-3066-0000-000000000000</groupId>
                        <id>406d35c8-7f6f-336c-0000-000000000000</id>
                        <type>INPUT_PORT</type>
                    </source>
                    <zIndex>0</zIndex>
                </connections>
                <connections>
                    <id>a57649be-c400-3eec-0000-000000000000</id>
                    <parentGroupId>c58e1e77-0375-3066-0000-000000000000</parentGroupId>
                    <backPressureDataSizeThreshold>1 GB</backPressureDataSizeThreshold>
                    <backPressureObjectThreshold>10000</backPressureObjectThreshold>
                    <destination>
                        <groupId>c58e1e77-0375-3066-0000-000000000000</groupId>
                        <id>9eacc986-9f6e-3c13-0000-000000000000</id>
                        <type>OUTPUT_PORT</type>
                    </destination>
                    <flowFileExpiration>0 sec</flowFileExpiration>
                    <labelIndex>1</labelIndex>
                    <loadBalanceCompression>DO_NOT_COMPRESS</loadBalanceCompression>
                    <loadBalancePartitionAttribute></loadBalancePartitionAttribute>
                    <loadBalanceStatus>LOAD_BALANCE_NOT_CONFIGURED</loadBalanceStatus>
                    <loadBalanceStrategy>DO_NOT_LOAD_BALANCE</loadBalanceStrategy>
                    <name></name>
                    <selectedRelationships>success</selectedRelationships>
                    <source>
                        <groupId>c58e1e77-0375-3066-0000-000000000000</groupId>
                        <id>352e925a-21f3-3ca2-0000-000000000000</id>
                        <type>PROCESSOR</type>
                    </source>
                    <zIndex>0</zIndex>
                </connections>
                <connections>
                    <id>ac4f458b-e3bd-3ca8-0000-000000000000</id>
                    <parentGroupId>c58e1e77-0375-3066-0000-000000000000</parentGroupId>
                    <backPressureDataSizeThreshold>1 GB</backPressureDataSizeThreshold>
                    <backPressureObjectThreshold>10000</backPressureObjectThreshold>
                    <destination>
                        <groupId>c58e1e77-0375-3066-0000-000000000000</groupId>
                        <id>a5d8a278-7af8-36c4-0000-000000000000</id>
                        <type>FUNNEL</type>
                    </destination>
                    <flowFileExpiration>0 sec</flowFileExpiration>
                    <labelIndex>1</labelIndex>
                    <loadBalanceCompression>DO_NOT_COMPRESS</loadBalanceCompression>
                    <loadBalancePartitionAttribute></loadBalancePartitionAttribute>
                    <loadBalanceStatus>LOAD_BALANCE_NOT_CONFIGURED</loadBalanceStatus>
                    <loadBalanceStrategy>DO_NOT_LOAD_BALANCE</loadBalanceStrategy>
                    <name></name>
                    <selectedRelationships>failure</selectedRelationships>
                    <source>
                        <groupId>c58e1e77-0375-3066-0000-000000000000</groupId>
                        <id>08cb882e-6c6c-3ae3-0000-000000000000</id>
                        <type>PROCESSOR</type>
                    </source>
                    <zIndex>0</zIndex>
                </connections>
                <funnels>
                    <id>a5d8a278-7af8-36c4-0000-000000000000</id>
                    <parentGroupId>c58e1e77-0375-3066-0000-000000000000</parentGroupId>
                    <position>
                        <x>1456.0</x>
                        <y>-128.0</y>
                    </position>
                </funnels>
                <inputPorts>
                    <id>406d35c8-7f6f-336c-0000-000000000000</id>
                    <parentGroupId>c58e1e77-0375-3066-0000-000000000000</parentGroupId>
                    <position>
                        <x>336.0</x>
                        <y>-120.0</y>
                    </position>
                    <concurrentlySchedulableTaskCount>1</concurrentlySchedulableTaskCount>
                    <name>FetchedFiles</name>
                    <state>STOPPED</state>
                    <type>INPUT_PORT</type>
                </inputPorts>
                <labels>
                    <id>9d5101f4-ac3e-3241-0000-000000000000</id>
                    <parentGroupId>c58e1e77-0375-3066-0000-000000000000</parentGroupId>
                    <position>
                        <x>736.0</x>
                        <y>-208.0</y>
                    </position>
                    <height>64.0</height>
                    <label>merge all the csv files into one</label>
                    <style>
                        <entry>
                            <key>font-size</key>
                            <value>16px</value>
                        </entry>
                    </style>
                    <width>280.0</width>
                </labels>
                <labels>
                    <id>e400c053-9310-3e0b-0000-000000000000</id>
                    <parentGroupId>c58e1e77-0375-3066-0000-000000000000</parentGroupId>
                    <position>
                        <x>1160.0</x>
                        <y>16.0</y>
                    </position>
                    <height>48.0</height>
                    <label>update filename attr</label>
                    <style>
                        <entry>
                            <key>font-size</key>
                            <value>16px</value>
                        </entry>
                    </style>
                    <width>184.0</width>
                </labels>
                <outputPorts>
                    <id>9eacc986-9f6e-3c13-0000-000000000000</id>
                    <parentGroupId>c58e1e77-0375-3066-0000-000000000000</parentGroupId>
                    <position>
                        <x>896.0</x>
                        <y>304.0</y>
                    </position>
                    <concurrentlySchedulableTaskCount>1</concurrentlySchedulableTaskCount>
                    <name>MergedFile</name>
                    <state>STOPPED</state>
                    <type>OUTPUT_PORT</type>
                </outputPorts>
                <processors>
                    <id>08cb882e-6c6c-3ae3-0000-000000000000</id>
                    <parentGroupId>c58e1e77-0375-3066-0000-000000000000</parentGroupId>
                    <position>
                        <x>840.0</x>
                        <y>-168.0</y>
                    </position>
                    <bundle>
                        <artifact>nifi-standard-nar</artifact>
                        <group>org.apache.nifi</group>
                        <version>1.12.1</version>
                    </bundle>
                    <config>
                        <bulletinLevel>WARN</bulletinLevel>
                        <comments></comments>
                        <concurrentlySchedulableTaskCount>1</concurrentlySchedulableTaskCount>
                        <descriptors>
                            <entry>
<key>Merge Strategy</key>
<value>
    <name>Merge Strategy</name>
</value>
                            </entry>
                            <entry>
<key>Merge Format</key>
<value>
    <name>Merge Format</name>
</value>
                            </entry>
                            <entry>
<key>Attribute Strategy</key>
<value>
    <name>Attribute Strategy</name>
</value>
                            </entry>
                            <entry>
<key>Correlation Attribute Name</key>
<value>
    <name>Correlation Attribute Name</name>
</value>
                            </entry>
                            <entry>
<key>mergecontent-metadata-strategy</key>
<value>
    <name>mergecontent-metadata-strategy</name>
</value>
                            </entry>
                            <entry>
<key>Minimum Number of Entries</key>
<value>
    <name>Minimum Number of Entries</name>
</value>
                            </entry>
                            <entry>
<key>Maximum Number of Entries</key>
<value>
    <name>Maximum Number of Entries</name>
</value>
                            </entry>
                            <entry>
<key>Minimum Group Size</key>
<value>
    <name>Minimum Group Size</name>
</value>
                            </entry>
                            <entry>
<key>Maximum Group Size</key>
<value>
    <name>Maximum Group Size</name>
</value>
                            </entry>
                            <entry>
<key>Max Bin Age</key>
<value>
    <name>Max Bin Age</name>
</value>
                            </entry>
                            <entry>
<key>Maximum number of Bins</key>
<value>
    <name>Maximum number of Bins</name>
</value>
                            </entry>
                            <entry>
<key>Delimiter Strategy</key>
<value>
    <name>Delimiter Strategy</name>
</value>
                            </entry>
                            <entry>
<key>Header File</key>
<value>
    <name>Header File</name>
</value>
                            </entry>
                            <entry>
<key>Footer File</key>
<value>
    <name>Footer File</name>
</value>
                            </entry>
                            <entry>
<key>Demarcator File</key>
<value>
    <name>Demarcator File</name>
</value>
                            </entry>
                            <entry>
<key>Compression Level</key>
<value>
    <name>Compression Level</name>
</value>
                            </entry>
                            <entry>
<key>Keep Path</key>
<value>
    <name>Keep Path</name>
</value>
                            </entry>
                            <entry>
<key>Tar Modified Time</key>
<value>
    <name>Tar Modified Time</name>
</value>
                            </entry>
                        </descriptors>
                        <executionNode>ALL</executionNode>
                        <lossTolerant>false</lossTolerant>
                        <penaltyDuration>30 sec</penaltyDuration>
                        <properties>
                            <entry>
<key>Merge Strategy</key>
<value>Bin-Packing Algorithm</value>
                            </entry>
                            <entry>
<key>Merge Format</key>
<value>Binary Concatenation</value>
                            </entry>
                            <entry>
<key>Attribute Strategy</key>
<value>Keep All Unique Attributes</value>
                            </entry>
                            <entry>
<key>Correlation Attribute Name</key>
                            </entry>
                            <entry>
<key>mergecontent-metadata-strategy</key>
<value>Do Not Merge Uncommon Metadata</value>
                            </entry>
                            <entry>
<key>Minimum Number of Entries</key>
<value>1</value>
                            </entry>
                            <entry>
<key>Maximum Number of Entries</key>
<value>1000</value>
                            </entry>
                            <entry>
<key>Minimum Group Size</key>
<value>0 B</value>
                            </entry>
                            <entry>
<key>Maximum Group Size</key>
                            </entry>
                            <entry>
<key>Max Bin Age</key>
                            </entry>
                            <entry>
<key>Maximum number of Bins</key>
<value>5</value>
                            </entry>
                            <entry>
<key>Delimiter Strategy</key>
<value>Filename</value>
                            </entry>
                            <entry>
<key>Header File</key>
                            </entry>
                            <entry>
<key>Footer File</key>
                            </entry>
                            <entry>
<key>Demarcator File</key>
                            </entry>
                            <entry>
<key>Compression Level</key>
<value>1</value>
                            </entry>
                            <entry>
<key>Keep Path</key>
<value>false</value>
                            </entry>
                            <entry>
<key>Tar Modified Time</key>
<value>${file.lastModifiedTime}</value>
                            </entry>
                        </properties>
                        <runDurationMillis>0</runDurationMillis>
                        <schedulingPeriod>0 sec</schedulingPeriod>
                        <schedulingStrategy>TIMER_DRIVEN</schedulingStrategy>
                        <yieldDuration>1 sec</yieldDuration>
                    </config>
                    <executionNodeRestricted>false</executionNodeRestricted>
                    <name>MergeContent</name>
                    <relationships>
                        <autoTerminate>false</autoTerminate>
                        <name>failure</name>
                    </relationships>
                    <relationships>
                        <autoTerminate>false</autoTerminate>
                        <name>merged</name>
                    </relationships>
                    <relationships>
                        <autoTerminate>true</autoTerminate>
                        <name>original</name>
                    </relationships>
                    <state>STOPPED</state>
                    <style/>
                    <type>org.apache.nifi.processors.standard.MergeContent</type>
                </processors>
                <processors>
                    <id>352e925a-21f3-3ca2-0000-000000000000</id>
                    <parentGroupId>c58e1e77-0375-3066-0000-000000000000</parentGroupId>
                    <position>
                        <x>840.0</x>
                        <y>48.0</y>
                    </position>
                    <bundle>
                        <artifact>nifi-update-attribute-nar</artifact>
                        <group>org.apache.nifi</group>
                        <version>1.12.1</version>
                    </bundle>
                    <config>
                        <bulletinLevel>WARN</bulletinLevel>
                        <comments></comments>
                        <concurrentlySchedulableTaskCount>1</concurrentlySchedulableTaskCount>
                        <descriptors>
                            <entry>
<key>Delete Attributes Expression</key>
<value>
    <name>Delete Attributes Expression</name>
</value>
                            </entry>
                            <entry>
<key>Store State</key>
<value>
    <name>Store State</name>
</value>
                            </entry>
                            <entry>
<key>Stateful Variables Initial Value</key>
<value>
    <name>Stateful Variables Initial Value</name>
</value>
                            </entry>
                            <entry>
<key>canonical-value-lookup-cache-size</key>
<value>
    <name>canonical-value-lookup-cache-size</name>
</value>
                            </entry>
                            <entry>
<key>filename</key>
<value>
    <name>filename</name>
</value>
                            </entry>
                        </descriptors>
                        <executionNode>ALL</executionNode>
                        <lossTolerant>false</lossTolerant>
                        <penaltyDuration>30 sec</penaltyDuration>
                        <properties>
                            <entry>
<key>Delete Attributes Expression</key>
                            </entry>
                            <entry>
<key>Store State</key>
<value>Do not store state</value>
                            </entry>
                            <entry>
<key>Stateful Variables Initial Value</key>
                            </entry>
                            <entry>
<key>canonical-value-lookup-cache-size</key>
<value>100</value>
                            </entry>
                            <entry>
<key>filename</key>
<value>merged.csv</value>
                            </entry>
                        </properties>
                        <runDurationMillis>0</runDurationMillis>
                        <schedulingPeriod>0 sec</schedulingPeriod>
                        <schedulingStrategy>TIMER_DRIVEN</schedulingStrategy>
                        <yieldDuration>1 sec</yieldDuration>
                    </config>
                    <executionNodeRestricted>false</executionNodeRestricted>
                    <name>UpdateAttribute</name>
                    <relationships>
                        <autoTerminate>false</autoTerminate>
                        <name>success</name>
                    </relationships>
                    <state>STOPPED</state>
                    <style/>
                    <type>org.apache.nifi.processors.attributes.UpdateAttribute</type>
                </processors>
            </contents>
            <flowfileConcurrency>UNBOUNDED</flowfileConcurrency>
            <flowfileOutboundPolicy>STREAM_WHEN_AVAILABLE</flowfileOutboundPolicy>
            <name>Mergefiles</name>
            <variables/>
        </processGroups>
    </snippet>
    <timestamp>02/09/2021 07:23:40 IST</timestamp>
</template>
